oneNeuron/__init__.py
oneNeuron/allutils.py
oneNeuron/perceptron.py
oneNeuron_pypi_kkkumar2-0.0.5.dist-info/LICENSE
oneNeuron_pypi_kkkumar2-0.0.5.dist-info/METADATA
oneNeuron_pypi_kkkumar2-0.0.5.dist-info/WHEEL
oneNeuron_pypi_kkkumar2-0.0.5.dist-info/top_level.txt
oneNeuron_pypi_kkkumar2-0.0.5.dist-info/RECORD
