Metadata-Version: 2.1
Name: oneNeuron-pypi-kkkumar2
Version: 0.0.5
Summary: This is a Single layer Perceptron package
Home-page: https://github.com/kkkumar2/oneNeuron_pypi
Author: kkkumar2
Author-email: kmohankumar123456@gmail.com
License: UNKNOWN
Project-URL: Bug Tracker, https://github.com/kkkumar2/oneNeuron_pypi
Platform: UNKNOWN
Classifier: Programming Language :: Python :: 3
Classifier: License :: OSI Approved :: MIT License
Classifier: Operating System :: OS Independent
Requires-Python: >=3.7
License-File: LICENSE
Requires-Dist: numpy
Requires-Dist: tqdm
Requires-Dist: pandas
Requires-Dist: matplotlib
Requires-Dist: logging
Requires-Dist: joblib
